[{"model": "bands.musician", "pk": 1, "fields": {"first_name": "Steve", "last_name": "Vai", "birth": "1960-06-06"}}, {"model": "bands.musician", "pk": 2, "fields": {"first_name": "John", "last_name": "Lennon", "birth": "1940-10-09"}}, {"model": "bands.musician", "pk": 3, "fields": {"first_name": "John", "last_name": "Bonham", "birth": "1948-07-31"}}, {"model": "bands.band", "pk": 1, "fields": {"name": "The Beatles", "musicians": [2]}}, {"model": "bands.band", "pk": 2, "fields": {"name": "Wishful Thinking", "musicians": [1, 2, 3]}}, {"model": "bands.venue", "pk": 1, "fields": {"name": "CBGB"}}, {"model": "bands.room", "pk": 1, "fields": {"name": "Red", "venue": 1}}, {"model": "bands.room", "pk": 2, "fields": {"name": "Blue", "venue": 1}}]
